ocr_tesseract_wrapper/__init__.py
ocr_tesseract_wrapper/ocr.py
ocr_tesseract_wrapper/text_detectors.py
ocr_tesseract_wrapper/transformations.py
ocr_tesseract_wrapper-0.0.8.dist-info/LICENSE
ocr_tesseract_wrapper-0.0.8.dist-info/METADATA
ocr_tesseract_wrapper-0.0.8.dist-info/WHEEL
ocr_tesseract_wrapper-0.0.8.dist-info/top_level.txt
ocr_tesseract_wrapper-0.0.8.dist-info/RECORD
