Metadata-Version: 2.1
Name: ocr-tesseract-wrapper
Version: 0.0.8
Summary: Tiny wrapper around pytesseract with image preprocessing and OCR configurations
Home-page: https://github.com/pjalusic/ocr-tesseract-wrapper
Author: Petar Jalusic
Author-email: pjalusic@gmail.com
License: UNKNOWN
Platform: UNKNOWN
Classifier: Programming Language :: Python :: 3
Classifier: License :: OSI Approved :: MIT License
Classifier: Operating System :: OS Independent
Requires-Python: >=3.6
Requires-Dist: pytesseract
Requires-Dist: Pillow
